Metadata-Version: 2.1
Name: odoo-addon-l10n_es_sigaus_stock_picking_report_valued
Version: 16.0.1.0.2.1
Summary: Show SIGAUS amount in valued stock pickings.
Home-page: https://github.com/OCA/l10n-spain
Author: Sygel, Odoo Community Association (OCA)
Author-email: support@odoo-community.org
License: AGPL-3
Classifier: Programming Language :: Python
Classifier: Framework :: Odoo
Classifier: Framework :: Odoo :: 16.0
Classifier: License :: OSI Approved :: GNU Affero General Public License v3
Requires-Python: >=3.10
Requires-Dist: odoo-addon-l10n-es-sigaus-sale<16.1dev,>=16.0dev
Requires-Dist: odoo-addon-stock-picking-report-valued<16.1dev,>=16.0dev
Requires-Dist: odoo<16.1dev,>=16.0a
